i2c_slave.v
module i2c_slave (
	input wire clk,              //clock input
	input wire rst_n,            //asynchronous reset input, low active
    input wire pin_scl,
    inout wire pin_sda,
    output reg [7:0] addr,
    output reg [7:0] data_in,//data_in means into device not into module
    output reg data_in_ready,//when high means that `data_in` needs to be saved on `addr`
    input wire [7:0] data_out,//data_out means out from device not out from module         NOT IMPLEMENTED
    output reg data_out_en,//high when expected value at address `addr` on data_out        NOT IMPLEMENTED
    input wire data_out_ready//when high can transfer data on i2c                          NOT IMPLEMENTED
);

reg sda_out;
assign pin_sda = sda_out ? 1'bz : 1'b0;

wire pin_scl_synced;
wire pin_sda_synced;

sync_pin sync_pin_scl(
    .pin(pin_scl),
    .clk(clk),
    .rst_n(rst_n),
    .pin_synced(pin_scl_synced)
);

sync_pin sync_pin_sda(
    .pin(pin_sda),
    .clk(clk),
    .rst_n(rst_n),
    .pin_synced(pin_sda_synced)
);

reg [5:0] state;
reg [5:0] next_state;
localparam IDLE = 5'b00000;
localparam RECIVING_ADDRESS = 5'b00001;
localparam RECIVING_DATA = 5'b00010;
localparam RECIVING_ADDRESS_ACK = 5'b00100;
localparam RECIVING_DATA_ACK = 5'b01000;

reg prev_sda;
reg prev_scl;

reg [2:0] counter; //counter is used for counting bits of recived address and data

always@(posedge clk or negedge rst_n) begin
    if(!rst_n) begin
        state <= IDLE;
    end
    else begin
        state <= next_state;
    end
end

always@(posedge clk or negedge rst_n) begin
    if (!rst_n) begin
        prev_sda = 1'b0;
        prev_scl = 1'b0;
        sda_out <= 1'b1;
        next_state <= IDLE;
        addr <= 8'b0;
        counter <= 3'b0;
        data_in <= 8'b0;
        data_in_ready <= 1'b0;
    end
    else begin
        prev_sda <= pin_sda_synced;
        prev_scl <= pin_scl_synced;
        
        if(state == IDLE) begin
            //START condition detection
            if((prev_sda == 1'b1 && pin_sda_synced == 1'b0) /* falling edge sda */ && (prev_scl == 1'b1 && pin_scl_synced == 1'b1) /* scl equals 1 */ ) begin
                next_state <= RECIVING_ADDRESS;
                counter <= 3'b111;
            end
        end
        if(state == RECIVING_ADDRESS) begin
            if(prev_scl == 1'b0 && pin_scl_synced == 1'b1 /* rising edge scl */) begin
                addr[counter] <= pin_sda_synced;
                counter <= counter - 1;
                if(counter == 0) begin
                    next_state <= RECIVING_ADDRESS_ACK;
                end
            end
        end
        if(state == RECIVING_DATA) begin
            if(pin_scl_synced == 1'b1 && (prev_sda == 1'b0 && pin_sda_synced == 1'b1)) begin
                next_state <= IDLE;
            end else if(prev_scl == 1'b0 && pin_scl_synced == 1'b1 /* rising edge scl */) begin
                //pun new information into data_in buffer and decrase counter
                data_in[counter] <= pin_sda_synced;
                counter <= counter - 1;
                if(counter == 0) begin
                    next_state <= RECIVING_DATA_ACK;
                    //give information to parent module that there is values in `data_in`
                    data_in_ready <= 1'b1;
                    //Incremet address for next byte
                    //if there is no next byte(STOP command on i2c) address will be eventauly overwrited
                    //if there is next byte it will be saved into `data_in` and putted into higher memory address
                    addr <= addr + 8'b1;
                end
            end
        end

        if(data_in_ready == 1'b1) begin
            data_in_ready <= 1'b0;
        end

        //ACK
        if(prev_scl == 1'b1 && pin_scl_synced == 1'b0 && (state == RECIVING_ADDRESS_ACK || state == RECIVING_DATA_ACK)) begin
            sda_out <= 1'b0;
        end
        if(prev_scl == 1'b1 && pin_scl_synced == 1'b0/* falling edge scl */ && sda_out == 1'b0) begin
            sda_out <= 1'b1;
            //chaning state for RECIVING_DATA after RECIVING_DATA_ACK to enable support for multi byte data transfer 
            if(state == RECIVING_ADDRESS_ACK || state == RECIVING_DATA_ACK) begin
                next_state <= RECIVING_DATA;
            end
        end
    end
end

endmodule

module sync_pin(
    input wire pin,
    input wire clk,
    input wire rst_n,
    output reg pin_synced
);

reg pin_metastable1;
reg pin_metastable2;


always @(posedge clk or negedge rst_n) begin
    if (!rst_n) begin
        pin_metastable1 <= 1'b0;
        pin_metastable2 <= 1'b0;
        pin_synced <= 1'b0;
    end else begin
        pin_metastable1 <= pin;
        pin_metastable2 <= pin_metastable1;
        pin_synced <= pin_metastable2;
    end
end

endmodule

testbeanch/i2c_slave_tb.v
module i2c_slave_tb;
initial
begin
    $dumpfile("i2c_slave_tb.vcd");
    $dumpvars(0, i2c_slave_tb);
end
reg reset_n = 1;

reg clk = 0;
always #1 clk = !clk;

reg pin_scl;
reg pin_sda_out;
reg pin_sda_out_en;
wire pin_sda;
assign pin_sda = pin_sda_out_en ? pin_sda_out : 1'bz;
wire[7:0] addr;
wire[7:0] data_in;
wire data_in_ready;

i2c_slave tested_module(
    .clk(clk),
    .rst_n(reset_n),
    .pin_scl(pin_scl),
    .pin_sda(pin_sda),
    .addr(addr),
    .data_in(data_in),//Data IN device
    .data_in_ready(data_in_ready)
);

task START;
begin
    pin_scl = 1;
    pin_sda_out = 1;
    #10 pin_sda_out = 0;
    #10 pin_scl = 0;
end
endtask

task ZERO;
begin
    #1 pin_sda_out = 0;
    #9 pin_scl = 1;
    #10 pin_scl = 0;
end
endtask

task ONE;
begin
    #1 pin_sda_out = 1;
    #9 pin_scl = 1;
    #10 pin_scl = 0;
end
endtask

always @(posedge data_in_ready) begin
    $display("  recived data: %b, recived address: %b", data_in, addr);
end

task SEND_DATA;
input integer exec_num;
begin
    $display("Starting execution %0d", exec_num);
    pin_sda_out_en = 1;
    
    #10 pin_scl = 1;
    #10 pin_scl = 0;

    pin_scl = 1;
    pin_sda_out = 1;

    #10 pin_sda_out = 0;
    pin_scl = 0;

    START();

    ZERO();
    ZERO();
    ONE();
    ONE();
    ZERO();
    ONE();
    ZERO();
    ONE();//WRITE

    pin_sda_out = 1'bz;//so it easier to see when pin_sda_out_en = 0
    pin_sda_out_en = 0;
    #10 pin_scl = 1;
    if (pin_sda !== 0) begin
        $display("  Recived NACK when expected ACK(1)");//it looks better than error in my opinion
    end else begin
        $display("  Recived ACK as expected(1)");
    end
    #10 pin_scl = 0;
    pin_sda_out_en = 1;
    
    ZERO();
    ONE();
    ONE();
    ONE();
    ZERO();
    ONE();
    ZERO();
    ONE();

    pin_sda_out = 1'bz;//so it easier to see when pin_sda_out_en = 0 on waveform
    pin_sda_out_en = 0;
    #10 pin_scl = 1;
    if (pin_sda !== 0) begin
        $display("  Recived NACK when expected ACK(2)");//it looks better than error in my opinion
    end else begin
        $display("  Recived ACK as expected(2)");
    end
    #10 pin_scl = 0;
    pin_sda_out_en = 1;

    ZERO();
    ONE();
    ONE();
    ONE();
    ZERO();
    ONE();
    ZERO();
    ZERO();

    pin_sda_out = 1'bz;//so it easier to see when pin_sda_out_en = 0 on waveform
    pin_sda_out_en = 0;
    #10 pin_scl = 1;
    if (pin_sda !== 0) begin
        $display("  Recived NACK when expected ACK(3)");//it looks better than error in my opinion
    end else begin
        $display("  Recived ACK as expected(3)");
    end
    #10 pin_scl = 0;
    pin_sda_out_en = 1;

    #10 pin_scl = 1;
    #10 pin_scl = 0;


    //Need to be set 0 beacuse it is `z` now.
    pin_sda_out = 0;
    pin_scl = 1;
    #10 pin_sda_out = 1;

    $display("Ended execution %0d", exec_num);
end
endtask

initial
begin
    reset_n = 0;
    #10 reset_n = 1;
    
    SEND_DATA(1);
    SEND_DATA(2);

    #40 $finish;
end
endmodule

testbeanch/i2c_slave_tb.vcd
$date
	Mon Jan  6 20:20:06 2025
$end
$version
	Icarus Verilog
$end
$timescale
	1s
$end
$scope module i2c_slave_tb $end
$var wire 1 ! pin_sda $end
$var wire 1 " data_in_ready $end
$var wire 8 # data_in [7:0] $end
$var wire 8 $ addr [7:0] $end
$var reg 1 % clk $end
$var reg 1 & pin_scl $end
$var reg 1 ' pin_sda_out $end
$var reg 1 ( pin_sda_out_en $end
$var reg 1 ) reset_n $end
$scope module tested_module $end
$var wire 1 % clk $end
$var wire 8 * data_out [7:0] $end
$var wire 1 + data_out_ready $end
$var wire 1 & pin_scl $end
$var wire 1 ! pin_sda $end
$var wire 1 ) rst_n $end
$var wire 1 , pin_sda_synced $end
$var wire 1 - pin_scl_synced $end
$var parameter 5 . IDLE $end
$var parameter 5 / RECIVING_ADDRESS $end
$var parameter 5 0 RECIVING_ADDRESS_ACK $end
$var parameter 5 1 RECIVING_DATA $end
$var parameter 5 2 RECIVING_DATA_ACK $end
$var reg 8 3 addr [7:0] $end
$var reg 3 4 counter [2:0] $end
$var reg 8 5 data_in [7:0] $end
$var reg 1 " data_in_ready $end
$var reg 1 6 data_out_en $end
$var reg 6 7 next_state [5:0] $end
$var reg 1 8 prev_scl $end
$var reg 1 9 prev_sda $end
$var reg 1 : sda_out $end
$var reg 6 ; state [5:0] $end
$scope module sync_pin_scl $end
$var wire 1 % clk $end
$var wire 1 & pin $end
$var wire 1 ) rst_n $end
$var reg 1 < pin_metastable1 $end
$var reg 1 = pin_metastable2 $end
$var reg 1 - pin_synced $end
$upscope $end
$scope module sync_pin_sda $end
$var wire 1 % clk $end
$var wire 1 ! pin $end
$var wire 1 ) rst_n $end
$var reg 1 > pin_metastable1 $end
$var reg 1 ? pin_metastable2 $end
$var reg 1 , pin_synced $end
$upscope $end
$upscope $end
$scope task ONE $end
$upscope $end
$scope task SEND_DATA $end
$var integer 32 @ exec_num [31:0] $end
$upscope $end
$scope task START $end
$upscope $end
$scope task ZERO $end
$upscope $end
$upscope $end
$enddefinitions $end
$comment Show the parameter values. $end
$dumpall
b1000 2
b10 1
b100 0
b1 /
b0 .
$end
#0
$dumpvars
bx @
0?
0>
0=
0<
b0 ;
1:
09
08
b0 7
x6
b0 5
b0 4
b0 3
0-
0,
z+
bz *
0)
x(
x'
x&
0%
b0 $
b0 #
0"
x!
$end
#1
1%
#2
0%
#3
1%
#4
0%
#5
1%
#6
0%
#7
1%
#8
0%
#9
1%
#10
0%
1(
b1 @
1)
#11
x<
x>
1%
#12
0%
#13
x?
x=
1%
#14
0%
#15
x-
x,
1%
#16
0%
#17
x8
x9
1%
#18
0%
#19
1%
#20
0%
1&
#21
1<
1%
#22
0%
#23
1=
1%
#24
0%
#25
1-
1%
#26
0%
#27
18
1%
#28
0%
#29
1%
#30
1!
0%
1'
1&
#31
1>
1%
#32
0%
#33
1?
1%
#34
0%
#35
1,
1%
#36
0%
#37
19
1%
#38
0%
#39
1%
#40
0%
1&
1'
#41
1%
#42
0%
#43
1%
#44
0%
#45
1%
#46
0%
#47
1%
#48
0%
#49
1%
#50
0!
0%
0'
#51
0>
1%
#52
0%
#53
0?
1%
#54
0%
#55
0,
1%
#56
0%
#57
b111 4
b1 7
09
1%
#58
0%
#59
b1 ;
1%
#60
0%
0&
#61
0<
1%
#62
0%
#63
0=
1%
#64
0%
#65
0-
1%
#66
0%
#67
08
1%
#68
0%
#69
1%
#70
0%
1&
#71
1<
1%
#72
0%
#73
1=
1%
#74
0%
#75
1-
1%
#76
0%
#77
b110 4
18
1%
#78
0%
#79
1%
#80
0%
0&
#81
0<
1%
#82
0%
#83
0=
1%
#84
0%
#85
0-
1%
#86
0%
#87
08
1%
#88
0%
#89
1%
#90
0%
1&
#91
1<
1%
#92
0%
#93
1=
1%
#94
0%
#95
1-
1%
#96
0%
#97
b101 4
18
1%
#98
0%
#99
1%
#100
0%
0&
#101
1>
0<
1!
1%
1'
#102
0%
#103
0=
1?
1%
#104
0%
#105
1,
0-
1%
#106
0%
#107
08
19
1%
#108
0%
#109
1%
#110
0%
1&
#111
1<
1%
#112
0%
#113
1=
1%
#114
0%
#115
1-
1%
#116
0%
#117
b100 4
b100000 $
b100000 3
18
1%
#118
0%
#119
1%
#120
0%
0&
#121
0<
1%
#122
0%
#123
0=
1%
#124
0%
#125
0-
1%
#126
0%
#127
08
1%
#128
0%
#129
1%
#130
0%
1&
#131
1<
1%
#132
0%
#133
1=
1%
#134
0%
#135
1-
1%
#136
0%
#137
b11 4
b110000 $
b110000 3
18
1%
#138
0%
#139
1%
#140
0%
0&
#141
0>
0<
0!
1%
0'
#142
0%
#143
0=
0?
1%
#144
0%
#145
0,
0-
1%
#146
0%
#147
08
09
1%
#148
0%
#149
1%
#150
0%
1&
#151
1<
1%
#152
0%
#153
1=
1%
#154
0%
#155
1-
1%
#156
0%
#157
b10 4
18
1%
#158
0%
#159
1%
#160
0%
0&
#161
1>
0<
1!
1%
1'
#162
0%
#163
0=
1?
1%
#164
0%
#165
1,
0-
1%
#166
0%
#167
08
19
1%
#168
0%
#169
1%
#170
0%
1&
#171
1<
1%
#172
0%
#173
1=
1%
#174
0%
#175
1-
1%
#176
0%
#177
b1 4
b110100 $
b110100 3
18
1%
#178
0%
#179
1%
#180
0%
0&
#181
0>
0<
0!
1%
0'
#182
0%
#183
0=
0?
1%
#184
0%
#185
0,
0-
1%
#186
0%
#187
08
09
1%
#188
0%
#189
1%
#190
0%
1&
#191
1<
1%
#192
0%
#193
1=
1%
#194
0%
#195
1-
1%
#196
0%
#197
b0 4
18
1%
#198
0%
#199
1%
#200
0%
0&
#201
1>
0<
1!
1%
1'
#202
0%
#203
0=
1?
1%
#204
0%
#205
1,
0-
1%
#206
0%
#207
08
19
1%
#208
0%
#209
1%
#210
0%
1&
#211
1<
1%
#212
0%
#213
1=
1%
#214
0%
#215
1-
1%
#216
0%
#217
b100 7
b111 4
b110101 $
b110101 3
18
1%
#218
0%
#219
b100 ;
1%
#220
z!
0%
0(
z'
0&
#221
z>
0<
1%
#222
0%
#223
0=
z?
1%
#224
0%
#225
z,
0-
1%
#226
0%
#227
0!
0:
08
z9
1%
#228
0%
#229
0>
1%
#230
0%
1&
#231
1<
0?
1%
#232
0%
#233
0,
1=
1%
#234
0%
#235
1-
09
1%
#236
0%
#237
18
1%
#238
0%
#239
1%
#240
0%
1(
0&
#241
0<
1%
0'
#242
0%
#243
0=
1%
#244
0%
#245
0-
1%
#246
0%
#247
b10 7
1:
08
1%
#248
0%
#249
b10 ;
1%
#250
0%
1&
#251
1<
1%
#252
0%
#253
1=
1%
#254
0%
#255
1-
1%
#256
0%
#257
b110 4
18
1%
#258
0%
#259
1%
#260
0%
0&
#261
1>
0<
1!
1%
1'
#262
0%
#263
0=
1?
1%
#264
0%
#265
1,
0-
1%
#266
0%
#267
08
19
1%
#268
0%
#269
1%
#270
0%
1&
#271
1<
1%
#272
0%
#273
1=
1%
#274
0%
#275
1-
1%
#276
0%
#277
b101 4
b1000000 #
b1000000 5
18
1%
#278
0%
#279
1%
#280
0%
0&
#281
0<
1%
#282
0%
#283
0=
1%
#284
0%
#285
0-
1%
#286
0%
#287
08
1%
#288
0%
#289
1%
#290
0%
1&
#291
1<
1%
#292
0%
#293
1=
1%
#294
0%
#295
1-
1%
#296
0%
#297
b100 4
b1100000 #
b1100000 5
18
1%
#298
0%
#299
1%
#300
0%
0&
#301
0<
1%
#302
0%
#303
0=
1%
#304
0%
#305
0-
1%
#306
0%
#307
08
1%
#308
0%
#309
1%
#310
0%
1&
#311
1<
1%
#312
0%
#313
1=
1%
#314
0%
#315
1-
1%
#316
0%
#317
b11 4
b1110000 #
b1110000 5
18
1%
#318
0%
#319
1%
#320
0%
0&
#321
0>
0<
0!
1%
0'
#322
0%
#323
0=
0?
1%
#324
0%
#325
0,
0-
1%
#326
0%
#327
08
09
1%
#328
0%
#329
1%
#330
0%
1&
#331
1<
1%
#332
0%
#333
1=
1%
#334
0%
#335
1-
1%
#336
0%
#337
b10 4
18
1%
#338
0%
#339
1%
#340
0%
0&
#341
1>
0<
1!
1%
1'
#342
0%
#343
0=
1?
1%
#344
0%
#345
1,
0-
1%
#346
0%
#347
08
19
1%
#348
0%
#349
1%
#350
0%
1&
#351
1<
1%
#352
0%
#353
1=
1%
#354
0%
#355
1-
1%
#356
0%
#357
b1 4
b1110100 #
b1110100 5
18
1%
#358
0%
#359
1%
#360
0%
0&
#361
0>
0<
0!
1%
0'
#362
0%
#363
0=
0?
1%
#364
0%
#365
0,
0-
1%
#366
0%
#367
08
09
1%
#368
0%
#369
1%
#370
0%
1&
#371
1<
1%
#372
0%
#373
1=
1%
#374
0%
#375
1-
1%
#376
0%
#377
b0 4
18
1%
#378
0%
#379
1%
#380
0%
0&
#381
1>
0<
1!
1%
1'
#382
0%
#383
0=
1?
1%
#384
0%
#385
1,
0-
1%
#386
0%
#387
08
19
1%
#388
0%
#389
1%
#390
0%
1&
#391
1<
1%
#392
0%
#393
1=
1%
#394
0%
#395
1-
1%
#396
0%
#397
b110110 $
b110110 3
1"
b1000 7
b111 4
b1110101 #
b1110101 5
18
1%
#398
0%
#399
b1000 ;
0"
1%
#400
z!
0%
0(
z'
0&
#401
z>
0<
1%
#402
0%
#403
0=
z?
1%
#404
0%
#405
z,
0-
1%
#406
0%
#407
0!
0:
08
z9
1%
#408
0%
#409
0>
1%
#410
0%
1&
#411
1<
0?
1%
#412
0%
#413
0,
1=
1%
#414
0%
#415
1-
09
1%
#416
0%
#417
18
1%
#418
0%
#419
1%
#420
0%
1(
0&
#421
0<
1%
0'
#422
0%
#423
0=
1%
#424
0%
#425
0-
1%
#426
0%
#427
b10 7
1:
08
1%
#428
0%
#429
b10 ;
1%
#430
0%
1&
#431
1<
1%
#432
0%
#433
1=
1%
#434
0%
#435
1-
1%
#436
0%
#437
b110 4
18
1%
#438
0%
#439
1%
#440
0%
0&
#441
1>
0<
1!
1%
1'
#442
0%
#443
0=
1?
1%
#444
0%
#445
1,
0-
1%
#446
0%
#447
08
19
1%
#448
0%
#449
1%
#450
0%
1&
#451
1<
1%
#452
0%
#453
1=
1%
#454
0%
#455
1-
1%
#456
0%
#457
b101 4
18
1%
#458
0%
#459
1%
#460
0%
0&
#461
0<
1%
#462
0%
#463
0=
1%
#464
0%
#465
0-
1%
#466
0%
#467
08
1%
#468
0%
#469
1%
#470
0%
1&
#471
1<
1%
#472
0%
#473
1=
1%
#474
0%
#475
1-
1%
#476
0%
#477
b100 4
18
1%
#478
0%
#479
1%
#480
0%
0&
#481
0<
1%
#482
0%
#483
0=
1%
#484
0%
#485
0-
1%
#486
0%
#487
08
1%
#488
0%
#489
1%
#490
0%
1&
#491
1<
1%
#492
0%
#493
1=
1%
#494
0%
#495
1-
1%
#496
0%
#497
b11 4
18
1%
#498
0%
#499
1%
#500
0%
0&
#501
0>
0<
0!
1%
0'
#502
0%
#503
0=
0?
1%
#504
0%
#505
0,
0-
1%
#506
0%
#507
08
09
1%
#508
0%
#509
1%
#510
0%
1&
#511
1<
1%
#512
0%
#513
1=
1%
#514
0%
#515
1-
1%
#516
0%
#517
b10 4
18
1%
#518
0%
#519
1%
#520
0%
0&
#521
1>
0<
1!
1%
1'
#522
0%
#523
0=
1?
1%
#524
0%
#525
1,
0-
1%
#526
0%
#527
08
19
1%
#528
0%
#529
1%
#530
0%
1&
#531
1<
1%
#532
0%
#533
1=
1%
#534
0%
#535
1-
1%
#536
0%
#537
b1 4
18
1%
#538
0%
#539
1%
#540
0%
0&
#541
0>
0<
0!
1%
0'
#542
0%
#543
0=
0?
1%
#544
0%
#545
0,
0-
1%
#546
0%
#547
08
09
1%
#548
0%
#549
1%
#550
0%
1&
#551
1<
1%
#552
0%
#553
1=
1%
#554
0%
#555
1-
1%
#556
0%
#557
b0 4
18
1%
#558
0%
#559
1%
#560
0%
0&
#561
0<
1%
#562
0%
#563
0=
1%
#564
0%
#565
0-
1%
#566
0%
#567
08
1%
#568
0%
#569
1%
#570
0%
1&
#571
1<
1%
#572
0%
#573
1=
1%
#574
0%
#575
1-
1%
#576
0%
#577
b110111 $
b110111 3
1"
b1000 7
b111 4
b1110100 #
b1110100 5
18
1%
#578
0%
#579
b1000 ;
0"
1%
#580
z!
0%
0(
z'
0&
#581
z>
0<
1%
#582
0%
#583
0=
z?
1%
#584
0%
#585
z,
0-
1%
#586
0%
#587
0!
0:
08
z9
1%
#588
0%
#589
0>
1%
#590
0%
1&
#591
1<
0?
1%
#592
0%
#593
0,
1=
1%
#594
0%
#595
1-
09
1%
#596
0%
#597
18
1%
#598
0%
#599
1%
#600
0%
1(
0&
#601
0<
1%
#602
0%
#603
0=
1%
#604
0%
#605
0-
1%
#606
0%
#607
z!
b10 7
1:
08
1%
#608
0%
#609
b10 ;
z>
1%
#610
0%
1&
#611
1<
z?
1%
#612
0%
#613
z,
1=
1%
#614
0%
#615
1-
z9
1%
#616
0%
#617
b110 4
bz1110100 #
bz1110100 5
18
1%
#618
0%
#619
1%
#620
0!
0%
0'
1&
#621
0>
1%
#622
0%
#623
0?
1%
#624
0%
#625
0,
1%
#626
0%
#627
09
1%
#628
0%
#629
1%
#630
1!
0%
b10 @
1'
#631
1>
1%
#632
0%
#633
1?
1%
#634
0%
#635
1,
1%
#636
0%
#637
b0 7
19
1%
#638
0%
#639
b0 ;
1%
#640
0%
#641
1%
#642
0%
#643
1%
#644
0%
#645
1%
#646
0%
#647
1%
#648
0%
#649
1%
#650
0%
1&
#651
1%
#652
0%
#653
1%
#654
0%
#655
1%
#656
0%
#657
1%
#658
0%
#659
1%
#660
0%
1&
1'
#661
1%
#662
0%
#663
1%
#664
0%
#665
1%
#666
0%
#667
1%
#668
0%
#669
1%
#670
0!
0%
0'
#671
0>
1%
#672
0%
#673
0?
1%
#674
0%
#675
0,
1%
#676
0%
#677
b111 4
b1 7
09
1%
#678
0%
#679
b1 ;
1%
#680
0%
0&
#681
0<
1%
#682
0%
#683
0=
1%
#684
0%
#685
0-
1%
#686
0%
#687
08
1%
#688
0%
#689
1%
#690
0%
1&
#691
1<
1%
#692
0%
#693
1=
1%
#694
0%
#695
1-
1%
#696
0%
#697
b110 4
18
1%
#698
0%
#699
1%
#700
0%
0&
#701
0<
1%
#702
0%
#703
0=
1%
#704
0%
#705
0-
1%
#706
0%
#707
08
1%
#708
0%
#709
1%
#710
0%
1&
#711
1<
1%
#712
0%
#713
1=
1%
#714
0%
#715
1-
1%
#716
0%
#717
b101 4
18
1%
#718
0%
#719
1%
#720
0%
0&
#721
1>
0<
1!
1%
1'
#722
0%
#723
0=
1?
1%
#724
0%
#725
1,
0-
1%
#726
0%
#727
08
19
1%
#728
0%
#729
1%
#730
0%
1&
#731
1<
1%
#732
0%
#733
1=
1%
#734
0%
#735
1-
1%
#736
0%
#737
b100 4
18
1%
#738
0%
#739
1%
#740
0%
0&
#741
0<
1%
#742
0%
#743
0=
1%
#744
0%
#745
0-
1%
#746
0%
#747
08
1%
#748
0%
#749
1%
#750
0%
1&
#751
1<
1%
#752
0%
#753
1=
1%
#754
0%
#755
1-
1%
#756
0%
#757
b11 4
18
1%
#758
0%
#759
1%
#760
0%
0&
#761
0>
0<
0!
1%
0'
#762
0%
#763
0=
0?
1%
#764
0%
#765
0,
0-
1%
#766
0%
#767
08
09
1%
#768
0%
#769
1%
#770
0%
1&
#771
1<
1%
#772
0%
#773
1=
1%
#774
0%
#775
1-
1%
#776
0%
#777
b10 4
18
1%
#778
0%
#779
1%
#780
0%
0&
#781
1>
0<
1!
1%
1'
#782
0%
#783
0=
1?
1%
#784
0%
#785
1,
0-
1%
#786
0%
#787
08
19
1%
#788
0%
#789
1%
#790
0%
1&
#791
1<
1%
#792
0%
#793
1=
1%
#794
0%
#795
1-
1%
#796
0%
#797
b1 4
18
1%
#798
0%
#799
1%
#800
0%
0&
#801
0>
0<
0!
1%
0'
#802
0%
#803
0=
0?
1%
#804
0%
#805
0,
0-
1%
#806
0%
#807
08
09
1%
#808
0%
#809
1%
#810
0%
1&
#811
1<
1%
#812
0%
#813
1=
1%
#814
0%
#815
1-
1%
#816
0%
#817
b0 4
b110101 $
b110101 3
18
1%
#818
0%
#819
1%
#820
0%
0&
#821
1>
0<
1!
1%
1'
#822
0%
#823
0=
1?
1%
#824
0%
#825
1,
0-
1%
#826
0%
#827
08
19
1%
#828
0%
#829
1%
#830
0%
1&
#831
1<
1%
#832
0%
#833
1=
1%
#834
0%
#835
1-
1%
#836
0%
#837
b100 7
b111 4
18
1%
#838
0%
#839
b100 ;
1%
#840
z!
0%
0(
z'
0&
#841
z>
0<
1%
#842
0%
#843
0=
z?
1%
#844
0%
#845
z,
0-
1%
#846
0%
#847
0!
0:
08
z9
1%
#848
0%
#849
0>
1%
#850
0%
1&
#851
1<
0?
1%
#852
0%
#853
0,
1=
1%
#854
0%
#855
1-
09
1%
#856
0%
#857
18
1%
#858
0%
#859
1%
#860
0%
1(
0&
#861
0<
1%
0'
#862
0%
#863
0=
1%
#864
0%
#865
0-
1%
#866
0%
#867
b10 7
1:
08
1%
#868
0%
#869
b10 ;
1%
#870
0%
1&
#871
1<
1%
#872
0%
#873
1=
1%
#874
0%
#875
1-
1%
#876
0%
#877
b110 4
b1110100 #
b1110100 5
18
1%
#878
0%
#879
1%
#880
0%
0&
#881
1>
0<
1!
1%
1'
#882
0%
#883
0=
1?
1%
#884
0%
#885
1,
0-
1%
#886
0%
#887
08
19
1%
#888
0%
#889
1%
#890
0%
1&
#891
1<
1%
#892
0%
#893
1=
1%
#894
0%
#895
1-
1%
#896
0%
#897
b101 4
18
1%
#898
0%
#899
1%
#900
0%
0&
#901
0<
1%
#902
0%
#903
0=
1%
#904
0%
#905
0-
1%
#906
0%
#907
08
1%
#908
0%
#909
1%
#910
0%
1&
#911
1<
1%
#912
0%
#913
1=
1%
#914
0%
#915
1-
1%
#916
0%
#917
b100 4
18
1%
#918
0%
#919
1%
#920
0%
0&
#921
0<
1%
#922
0%
#923
0=
1%
#924
0%
#925
0-
1%
#926
0%
#927
08
1%
#928
0%
#929
1%
#930
0%
1&
#931
1<
1%
#932
0%
#933
1=
1%
#934
0%
#935
1-
1%
#936
0%
#937
b11 4
18
1%
#938
0%
#939
1%
#940
0%
0&
#941
0>
0<
0!
1%
0'
#942
0%
#943
0=
0?
1%
#944
0%
#945
0,
0-
1%
#946
0%
#947
08
09
1%
#948
0%
#949
1%
#950
0%
1&
#951
1<
1%
#952
0%
#953
1=
1%
#954
0%
#955
1-
1%
#956
0%
#957
b10 4
18
1%
#958
0%
#959
1%
#960
0%
0&
#961
1>
0<
1!
1%
1'
#962
0%
#963
0=
1?
1%
#964
0%
#965
1,
0-
1%
#966
0%
#967
08
19
1%
#968
0%
#969
1%
#970
0%
1&
#971
1<
1%
#972
0%
#973
1=
1%
#974
0%
#975
1-
1%
#976
0%
#977
b1 4
18
1%
#978
0%
#979
1%
#980
0%
0&
#981
0>
0<
0!
1%
0'
#982
0%
#983
0=
0?
1%
#984
0%
#985
0,
0-
1%
#986
0%
#987
08
09
1%
#988
0%
#989
1%
#990
0%
1&
#991
1<
1%
#992
0%
#993
1=
1%
#994
0%
#995
1-
1%
#996
0%
#997
b0 4
18
1%
#998
0%
#999
1%
#1000
0%
0&
#1001
1>
0<
1!
1%
1'
#1002
0%
#1003
0=
1?
1%
#1004
0%
#1005
1,
0-
1%
#1006
0%
#1007
08
19
1%
#1008
0%
#1009
1%
#1010
0%
1&
#1011
1<
1%
#1012
0%
#1013
1=
1%
#1014
0%
#1015
1-
1%
#1016
0%
#1017
b110110 $
b110110 3
1"
b1000 7
b111 4
b1110101 #
b1110101 5
18
1%
#1018
0%
#1019
b1000 ;
0"
1%
#1020
z!
0%
0(
z'
0&
#1021
z>
0<
1%
#1022
0%
#1023
0=
z?
1%
#1024
0%
#1025
z,
0-
1%
#1026
0%
#1027
0!
0:
08
z9
1%
#1028
0%
#1029
0>
1%
#1030
0%
1&
#1031
1<
0?
1%
#1032
0%
#1033
0,
1=
1%
#1034
0%
#1035
1-
09
1%
#1036
0%
#1037
18
1%
#1038
0%
#1039
1%
#1040
0%
1(
0&
#1041
0<
1%
0'
#1042
0%
#1043
0=
1%
#1044
0%
#1045
0-
1%
#1046
0%
#1047
b10 7
1:
08
1%
#1048
0%
#1049
b10 ;
1%
#1050
0%
1&
#1051
1<
1%
#1052
0%
#1053
1=
1%
#1054
0%
#1055
1-
1%
#1056
0%
#1057
b110 4
18
1%
#1058
0%
#1059
1%
#1060
0%
0&
#1061
1>
0<
1!
1%
1'
#1062
0%
#1063
0=
1?
1%
#1064
0%
#1065
1,
0-
1%
#1066
0%
#1067
08
19
1%
#1068
0%
#1069
1%
#1070
0%
1&
#1071
1<
1%
#1072
0%
#1073
1=
1%
#1074
0%
#1075
1-
1%
#1076
0%
#1077
b101 4
18
1%
#1078
0%
#1079
1%
#1080
0%
0&
#1081
0<
1%
#1082
0%
#1083
0=
1%
#1084
0%
#1085
0-
1%
#1086
0%
#1087
08
1%
#1088
0%
#1089
1%
#1090
0%
1&
#1091
1<
1%
#1092
0%
#1093
1=
1%
#1094
0%
#1095
1-
1%
#1096
0%
#1097
b100 4
18
1%
#1098
0%
#1099
1%
#1100
0%
0&
#1101
0<
1%
#1102
0%
#1103
0=
1%
#1104
0%
#1105
0-
1%
#1106
0%
#1107
08
1%
#1108
0%
#1109
1%
#1110
0%
1&
#1111
1<
1%
#1112
0%
#1113
1=
1%
#1114
0%
#1115
1-
1%
#1116
0%
#1117
b11 4
18
1%
#1118
0%
#1119
1%
#1120
0%
0&
#1121
0>
0<
0!
1%
0'
#1122
0%
#1123
0=
0?
1%
#1124
0%
#1125
0,
0-
1%
#1126
0%
#1127
08
09
1%
#1128
0%
#1129
1%
#1130
0%
1&
#1131
1<
1%
#1132
0%
#1133
1=
1%
#1134
0%
#1135
1-
1%
#1136
0%
#1137
b10 4
18
1%
#1138
0%
#1139
1%
#1140
0%
0&
#1141
1>
0<
1!
1%
1'
#1142
0%
#1143
0=
1?
1%
#1144
0%
#1145
1,
0-
1%
#1146
0%
#1147
08
19
1%
#1148
0%
#1149
1%
#1150
0%
1&
#1151
1<
1%
#1152
0%
#1153
1=
1%
#1154
0%
#1155
1-
1%
#1156
0%
#1157
b1 4
18
1%
#1158
0%
#1159
1%
#1160
0%
0&
#1161
0>
0<
0!
1%
0'
#1162
0%
#1163
0=
0?
1%
#1164
0%
#1165
0,
0-
1%
#1166
0%
